Sim/components.v
module lfsr_32bit (
    input clk,
    input rst_n,        // Active low reset
    input en,           // Enable shifting
    input [31:0] seed,  // Initial seed value
    input load_seed,    // Signal to load the seed
    output reg [31:0] rand_out
);

    // Polynomial: x^32 + x^22 + x^2 + x^1 + 1
    // Represents the tap positions for maximal length sequence
    localparam POLY = 32'h80200003; 

    always @(posedge clk or negedge rst_n) begin
        if (!rst_n) begin
            rand_out <= 32'hDEADBEEF; // Default non-zero seed
        end else if (load_seed) begin
            rand_out <= seed;
        end else if (en) begin
            if (rand_out[0] == 1'b1) begin
                rand_out <= (rand_out >> 1) ^ POLY;
            end else begin
                rand_out <= rand_out >> 1;
            end
        end
    end
endmodule

// ==========================================
// M10K BRAM Inference Module
// ==========================================
module log_add_rom (
    input wire clk,
    input wire [9:0] addr,
    output reg [31:0] data_out
);
    // Declare 1024 words of 32-bit memory
    reg [31:0] mem [0:1023];

    // Load the hex file. Both iverilog and Quartus support this.
    initial begin
        $readmemh("log_lut.hex", mem);
    end

    // Synchronous read (CRITICAL for Quartus M10K block inference)
    always @(posedge clk) begin
        data_out <= mem[addr];
    end
endmodule

// ==========================================
// Pipelined Log-Add Arithmetic Module
// ==========================================
module log_add (
    input wire clk,
    input wire rst_n,
    input wire signed [31:0] a, // Q16.16 format
    input wire signed [31:0] b, // Q16.16 format
    output reg signed [31:0] result
);

    // --- Stage 1 Registers ---
    reg signed [31:0] max_val_s1;
    reg [31:0] abs_diff_s1;

    // --- Stage 2 Registers ---
    reg signed [31:0] max_val_s2;
    wire [31:0] lut_val_s2;
    reg force_zero_s2; // Flag if diff is too large for LUT

    // Instantiate the ROM
    // The ROM has a 1-cycle latency. Address goes in at S1, data available at S2.
    log_add_rom lut_inst (
        .clk(clk),
        .addr(abs_diff_s1[19:10]), // Map diff to 10-bit address (diff / step_size)
        .data_out(lut_val_s2)
    );

    // PIPELINE LOGIC
    always @(posedge clk or negedge rst_n) begin
        if (!rst_n) begin
            max_val_s1  <= 0;
            abs_diff_s1 <= 0;
            max_val_s2  <= 0;
            force_zero_s2 <= 0;
            result      <= 0;
        end else begin
            // ==========================================
            // STAGE 1: Calculate Diff, Max, and Abs
            // ==========================================
            if (a > b) begin
                max_val_s1  <= a;
                abs_diff_s1 <= a - b;
            end else begin
                max_val_s1  <= b;
                abs_diff_s1 <= b - a;
            end

            // ==========================================
            // STAGE 2: Memory Read & Delay Matching
            // ==========================================
            // Pass max_val forward to align with the ROM read latency
            max_val_s2 <= max_val_s1;
            
            // If the absolute difference is >= 16.0 (0x00100000 in Q16.16)
            // The log(1+e^-x) is effectively 0. Clamp it to avoid memory overflow.
            if (abs_diff_s1 >= 32'h0010_0000) begin
                force_zero_s2 <= 1'b1;
            end else begin
                force_zero_s2 <= 1'b0;
            end

            // ==========================================
            // STAGE 3: Final Addition
            // ==========================================
            if (force_zero_s2) begin
                result <= max_val_s2; // Add 0
            end else begin
                result <= max_val_s2 + lut_val_s2;
            end
        end
    end
endmodule

verilog/tb_lsfr.v
`include "components.v"
`timescale 1ns / 1ps // Defines time units for simulation

module tb_lfsr_32bit();

    // 1. Declare testbench signals (regs for inputs, wires for outputs)
    reg clk;
    reg rst_n;
    reg en;
    reg [31:0] seed;
    reg load_seed;
    wire [31:0] rand_out;

    // 2. Instantiate the module under test (DUT - Device Under Test)
    lfsr_32bit uut (
        .clk(clk),
        .rst_n(rst_n),
        .en(en),
        .seed(seed),
        .load_seed(load_seed),
        .rand_out(rand_out)
    );

    // 3. Generate a clock (50MHz = 20ns period -> toggles every 10ns)
    always #10 clk = ~clk;

    // 4. Test Sequence
    initial begin
        // Initialize inputs
        clk = 0;
        rst_n = 0; // Assert reset (active low)
        en = 0;
        load_seed = 0;
        seed = 32'h12345678; // An arbitrary seed

        $dumpfile("tb_lsfr.vcd"); // Give the file a specific name
        $dumpvars(0, tb_lfsr_32bit);    // Dump everything in the module 'testbench'

        // Wait a bit, then release reset
        #50;
        rst_n = 1;

        // Load our custom seed
        #20;
        load_seed = 1;
        #20;
        load_seed = 0; // Stop loading

        // Enable shifting to generate numbers
        #20;
        en = 1;

        // Let it run for 20 clock cycles to watch the numbers change
        #4000;

        // Pause it
        en = 0;
        #40;

        // End simulation
        $finish;
    end

    // 5. Print the values to the console automatically
    always @(posedge clk) begin
        if (en) begin
            $display("Time: %0t | Random Value: %h", $time, rand_out);
        end
    end

endmodule

Sim/lsfr testing/tb_lsfr.vcd
$date
	Thu Apr 16 12:05:54 2026
$end
$version
	Icarus Verilog
$end
$timescale
	1ps
$end
$scope module tb_lfsr_32bit $end
$var wire 32 ! rand_out [31:0] $end
$var reg 1 " clk $end
$var reg 1 # en $end
$var reg 1 $ load_seed $end
$var reg 1 % rst_n $end
$var reg 32 & seed [31:0] $end
$scope module uut $end
$var wire 1 " clk $end
$var wire 1 # en $end
$var wire 1 $ load_seed $end
$var wire 1 % rst_n $end
$var wire 32 ' seed [31:0] $end
$var parameter 32 ( POLY $end
$var reg 32 ) rand_out [31:0] $end
$upscope $end
$upscope $end
$enddefinitions $end
$comment Show the parameter values. $end
$dumpall
b10000000001000000000000000000011 (
$end
#0
$dumpvars
b11011110101011011011111011101111 )
b10010001101000101011001111000 '
b10010001101000101011001111000 &
0%
0$
0#
0"
b11011110101011011011111011101111 !
$end
#10000
1"
#20000
0"
#30000
1"
#40000
0"
#50000
1"
1%
#60000
0"
#70000
b10010001101000101011001111000 !
b10010001101000101011001111000 )
1"
1$
#80000
0"
#90000
1"
0$
#100000
0"
#110000
b1001000110100010101100111100 !
b1001000110100010101100111100 )
1"
1#
#120000
0"
#130000
b100100011010001010110011110 !
b100100011010001010110011110 )
1"
#140000
0"
#150000
b10010001101000101011001111 !
b10010001101000101011001111 )
1"
#160000
0"
#170000
b10000001000000110100010101100100 !
b10000001000000110100010101100100 )
1"
#180000
0"
#190000
b1000000100000011010001010110010 !
b1000000100000011010001010110010 )
1"
#200000
0"
#210000
b100000010000001101000101011001 !
b100000010000001101000101011001 )
1"
#220000
0"
#230000
b10010000000000000110100010101111 !
b10010000000000000110100010101111 )
1"
#240000
0"
#250000
b11001000001000000011010001010100 !
b11001000001000000011010001010100 )
1"
#260000
0"
#270000
b1100100000100000001101000101010 !
b1100100000100000001101000101010 )
1"
#280000
0"
#290000
b110010000010000000110100010101 !
b110010000010000000110100010101 )
1"
#300000
0"
#310000
b10011001001001000000011010001001 !
b10011001001001000000011010001001 )
1"
#320000
0"
#330000
b11001100101100100000001101000111 !
b11001100101100100000001101000111 )
1"
#340000
0"
#350000
b11100110011110010000000110100000 !
b11100110011110010000000110100000 )
1"
#360000
0"
#370000
b1110011001111001000000011010000 !
b1110011001111001000000011010000 )
1"
#380000
0"
#390000
b111001100111100100000001101000 !
b111001100111100100000001101000 )
1"
#400000
0"
#410000
b11100110011110010000000110100 !
b11100110011110010000000110100 )
1"
#420000
0"
#430000
b1110011001111001000000011010 !
b1110011001111001000000011010 )
1"
#440000
0"
#450000
b111001100111100100000001101 !
b111001100111100100000001101 )
1"
#460000
0"
#470000
b10000011101110011110010000000101 !
b10000011101110011110010000000101 )
1"
#480000
0"
#490000
b11000001111111001111001000000001 !
b11000001111111001111001000000001 )
1"
#500000
0"
#510000
b11100000110111100111100100000011 !
b11100000110111100111100100000011 )
1"
#520000
0"
#530000
b11110000010011110011110010000010 !
b11110000010011110011110010000010 )
1"
#540000
0"
#550000
b1111000001001111001111001000001 !
b1111000001001111001111001000001 )
1"
#560000
0"
#570000
b10111100001100111100111100100011 !
b10111100001100111100111100100011 )
1"
#580000
0"
#590000
b11011110001110011110011110010010 !
b11011110001110011110011110010010 )
1"
#600000
0"
#610000
b1101111000111001111001111001001 !
b1101111000111001111001111001001 )
1"
#620000
0"
#630000
b10110111101011100111100111100111 !
b10110111101011100111100111100111 )
1"
#640000
0"
#650000
b11011011111101110011110011110000 !
b11011011111101110011110011110000 )
1"
#660000
0"
#670000
b1101101111110111001111001111000 !
b1101101111110111001111001111000 )
1"
#680000
0"
#690000
b110110111111011100111100111100 !
b110110111111011100111100111100 )
1"
#700000
0"
#710000
b11011011111101110011110011110 !
b11011011111101110011110011110 )
1"
#720000
0"
#730000
b1101101111110111001111001111 !
b1101101111110111001111001111 )
1"
#740000
0"
#750000
b10000110111111111011100111100100 !
b10000110111111111011100111100100 )
1"
#760000
0"
#770000
b1000011011111111101110011110010 !
b1000011011111111101110011110010 )
1"
#780000
0"
#790000
b100001101111111110111001111001 !
b100001101111111110111001111001 )
1"
#800000
0"
#810000
b10010000111111111111011100111111 !
b10010000111111111111011100111111 )
1"
#820000
0"
#830000
b11001000010111111111101110011100 !
b11001000010111111111101110011100 )
1"
#840000
0"
#850000
b1100100001011111111110111001110 !
b1100100001011111111110111001110 )
1"
#860000
0"
#870000
b110010000101111111111011100111 !
b110010000101111111111011100111 )
1"
#880000
0"
#890000
b10011001001010111111111101110000 !
b10011001001010111111111101110000 )
1"
#900000
0"
#910000
b1001100100101011111111110111000 !
b1001100100101011111111110111000 )
1"
#920000
0"
#930000
b100110010010101111111111011100 !
b100110010010101111111111011100 )
1"
#940000
0"
#950000
b10011001001010111111111101110 !
b10011001001010111111111101110 )
1"
#960000
0"
#970000
b1001100100101011111111110111 !
b1001100100101011111111110111 )
1"
#980000
0"
#990000
b10000100111010010101111111111000 !
b10000100111010010101111111111000 )
1"
#1000000
0"
#1010000
b1000010011101001010111111111100 !
b1000010011101001010111111111100 )
1"
#1020000
0"
#1030000
b100001001110100101011111111110 !
b100001001110100101011111111110 )
1"
#1040000
0"
#1050000
b10000100111010010101111111111 !
b10000100111010010101111111111 )
1"
#1060000
0"
#1070000
b10001000011011101001010111111100 !
b10001000011011101001010111111100 )
1"
#1080000
0"
#1090000
b1000100001101110100101011111110 !
b1000100001101110100101011111110 )
1"
#1100000
0"
#1110000
b100010000110111010010101111111 !
b100010000110111010010101111111 )
1"
#1120000
0"
#1130000
b10010001001011011101001010111100 !
b10010001001011011101001010111100 )
1"
#1140000
0"
#1150000
b1001000100101101110100101011110 !
b1001000100101101110100101011110 )
1"
#1160000
0"
#1170000
b100100010010110111010010101111 !
b100100010010110111010010101111 )
1"
#1180000
0"
#1190000
b10010010000001011011101001010100 !
b10010010000001011011101001010100 )
1"
#1200000
0"
#1210000
b1001001000000101101110100101010 !
b1001001000000101101110100101010 )
1"
#1220000
0"
#1230000
b100100100000010110111010010101 !
b100100100000010110111010010101 )
1"
#1240000
0"
#1250000
b10010010011000001011011101001001 !
b10010010011000001011011101001001 )
1"
#1260000
0"
#1270000
b11001001000100000101101110100111 !
b11001001000100000101101110100111 )
1"
#1280000
0"
#1290000
b11100100101010000010110111010000 !
b11100100101010000010110111010000 )
1"
#1300000
0"
#1310000
b1110010010101000001011011101000 !
b1110010010101000001011011101000 )
1"
#1320000
0"
#1330000
b111001001010100000101101110100 !
b111001001010100000101101110100 )
1"
#1340000
0"
#1350000
b11100100101010000010110111010 !
b11100100101010000010110111010 )
1"
#1360000
0"
#1370000
b1110010010101000001011011101 !
b1110010010101000001011011101 )
1"
#1380000
0"
#1390000
b10000111000001010100000101101101 !
b10000111000001010100000101101101 )
1"
#1400000
0"
#1410000
b11000011101000101010000010110101 !
b11000011101000101010000010110101 )
1"
#1420000
0"
#1430000
b11100001111100010101000001011001 !
b11100001111100010101000001011001 )
1"
#1440000
0"
#1450000
b11110000110110001010100000101111 !
b11110000110110001010100000101111 )
1"
#1460000
0"
#1470000
b11111000010011000101010000010100 !
b11111000010011000101010000010100 )
1"
#1480000
0"
#1490000
b1111100001001100010101000001010 !
b1111100001001100010101000001010 )
1"
#1500000
0"
#1510000
b111110000100110001010100000101 !
b111110000100110001010100000101 )
1"
#1520000
0"
#1530000
b10011111001010011000101010000001 !
b10011111001010011000101010000001 )
1"
#1540000
0"
#1550000
b11001111101101001100010101000011 !
b11001111101101001100010101000011 )
1"
#1560000
0"
#1570000
b11100111111110100110001010100010 !
b11100111111110100110001010100010 )
1"
#1580000
0"
#1590000
b1110011111111010011000101010001 !
b1110011111111010011000101010001 )
1"
#1600000
0"
#1610000
b10111001110111101001100010101011 !
b10111001110111101001100010101011 )
1"
#1620000
0"
#1630000
b11011100110011110100110001010110 !
b11011100110011110100110001010110 )
1"
#1640000
0"
#1650000
b1101110011001111010011000101011 !
b1101110011001111010011000101011 )
1"
#1660000
0"
#1670000
b10110111000100111101001100010110 !
b10110111000100111101001100010110 )
1"
#1680000
0"
#1690000
b1011011100010011110100110001011 !
b1011011100010011110100110001011 )
1"
#1700000
0"
#1710000
b10101101111001001111010011000110 !
b10101101111001001111010011000110 )
1"
#1720000
0"
#1730000
b1010110111100100111101001100011 !
b1010110111100100111101001100011 )
1"
#1740000
0"
#1750000
b10101011010110010011110100110010 !
b10101011010110010011110100110010 )
1"
#1760000
0"
#1770000
b1010101101011001001111010011001 !
b1010101101011001001111010011001 )
1"
#1780000
0"
#1790000
b10101010111101100100111101001111 !
b10101010111101100100111101001111 )
1"
#1800000
0"
#1810000
b11010101010110110010011110100100 !
b11010101010110110010011110100100 )
1"
#1820000
0"
#1830000
b1101010101011011001001111010010 !
b1101010101011011001001111010010 )
1"
#1840000
0"
#1850000
b110101010101101100100111101001 !
b110101010101101100100111101001 )
1"
#1860000
0"
#1870000
b10011010100010110110010011110111 !
b10011010100010110110010011110111 )
1"
#1880000
0"
#1890000
b11001101011001011011001001111000 !
b11001101011001011011001001111000 )
1"
#1900000
0"
#1910000
b1100110101100101101100100111100 !
b1100110101100101101100100111100 )
1"
#1920000
0"
#1930000
b110011010110010110110010011110 !
b110011010110010110110010011110 )
1"
#1940000
0"
#1950000
b11001101011001011011001001111 !
b11001101011001011011001001111 )
1"
#1960000
0"
#1970000
b10001100111101100101101100100100 !
b10001100111101100101101100100100 )
1"
#1980000
0"
#1990000
b1000110011110110010110110010010 !
b1000110011110110010110110010010 )
1"
#2000000
0"
#2010000
b100011001111011001011011001001 !
b100011001111011001011011001001 )
1"
#2020000
0"
#2030000
b10010001101111101100101101100111 !
b10010001101111101100101101100111 )
1"
#2040000
0"
#2050000
b11001000111111110110010110110000 !
b11001000111111110110010110110000 )
1"
#2060000
0"
#2070000
b1100100011111111011001011011000 !
b1100100011111111011001011011000 )
1"
#2080000
0"
#2090000
b110010001111111101100101101100 !
b110010001111111101100101101100 )
1"
#2100000
0"
#2110000
b11001000111111110110010110110 !
b11001000111111110110010110110 )
1"
#2120000
0"
#2130000
b1100100011111111011001011011 !
b1100100011111111011001011011 )
1"
#2140000
0"
#2150000
b10000110011001111111101100101110 !
b10000110011001111111101100101110 )
1"
#2160000
0"
#2170000
b1000011001100111111110110010111 !
b1000011001100111111110110010111 )
1"
#2180000
0"
#2190000
b10100001101110011111111011001000 !
b10100001101110011111111011001000 )
1"
#2200000
0"
#2210000
b1010000110111001111111101100100 !
b1010000110111001111111101100100 )
1"
#2220000
0"
#2230000
b101000011011100111111110110010 !
b101000011011100111111110110010 )
1"
#2240000
0"
#2250000
b10100001101110011111111011001 !
b10100001101110011111111011001 )
1"
#2260000
0"
#2270000
b10001010001110111001111111101111 !
b10001010001110111001111111101111 )
1"
#2280000
0"
#2290000
b11000101001111011100111111110100 !
b11000101001111011100111111110100 )
1"
#2300000
0"
#2310000
b1100010100111101110011111111010 !
b1100010100111101110011111111010 )
1"
#2320000
0"
#2330000
b110001010011110111001111111101 !
b110001010011110111001111111101 )
1"
#2340000
0"
#2350000
b10011000100001111011100111111101 !
b10011000100001111011100111111101 )
1"
#2360000
0"
#2370000
b11001100011000111101110011111101 !
b11001100011000111101110011111101 )
1"
#2380000
0"
#2390000
b11100110000100011110111001111101 !
b11100110000100011110111001111101 )
1"
#2400000
0"
#2410000
b11110011001010001111011100111101 !
b11110011001010001111011100111101 )
1"
#2420000
0"
#2430000
b11111001101101000111101110011101 !
b11111001101101000111101110011101 )
1"
#2440000
0"
#2450000
b11111100111110100011110111001101 !
b11111100111110100011110111001101 )
1"
#2460000
0"
#2470000
b11111110010111010001111011100101 !
b11111110010111010001111011100101 )
1"
#2480000
0"
#2490000
b11111111000011101000111101110001 !
b11111111000011101000111101110001 )
1"
#2500000
0"
#2510000
b11111111101001110100011110111011 !
b11111111101001110100011110111011 )
1"
#2520000
0"
#2530000
b11111111111100111010001111011110 !
b11111111111100111010001111011110 )
1"
#2540000
0"
#2550000
b1111111111110011101000111101111 !
b1111111111110011101000111101111 )
1"
#2560000
0"
#2570000
b10111111110111001110100011110100 !
b10111111110111001110100011110100 )
1"
#2580000
0"
#2590000
b1011111111011100111010001111010 !
b1011111111011100111010001111010 )
1"
#2600000
0"
#2610000
b101111111101110011101000111101 !
b101111111101110011101000111101 )
1"
#2620000
0"
#2630000
b10010111110110111001110100011101 !
b10010111110110111001110100011101 )
1"
#2640000
0"
#2650000
b11001011110011011100111010001101 !
b11001011110011011100111010001101 )
1"
#2660000
0"
#2670000
b11100101110001101110011101000101 !
b11100101110001101110011101000101 )
1"
#2680000
0"
#2690000
b11110010110000110111001110100001 !
b11110010110000110111001110100001 )
1"
#2700000
0"
#2710000
b11111001010000011011100111010011 !
b11111001010000011011100111010011 )
1"
#2720000
0"
#2730000
b11111100100000001101110011101010 !
b11111100100000001101110011101010 )
1"
#2740000
0"
#2750000
b1111110010000000110111001110101 !
b1111110010000000110111001110101 )
1"
#2760000
0"
#2770000
b10111111000000000011011100111001 !
b10111111000000000011011100111001 )
1"
#2780000
0"
#2790000
b11011111101000000001101110011111 !
b11011111101000000001101110011111 )
1"
#2800000
0"
#2810000
b11101111111100000000110111001100 !
b11101111111100000000110111001100 )
1"
#2820000
0"
#2830000
b1110111111110000000011011100110 !
b1110111111110000000011011100110 )
1"
#2840000
0"
#2850000
b111011111111000000001101110011 !
b111011111111000000001101110011 )
1"
#2860000
0"
#2870000
b10011101110111100000000110111010 !
b10011101110111100000000110111010 )
1"
#2880000
0"
#2890000
b1001110111011110000000011011101 !
b1001110111011110000000011011101 )
1"
#2900000
0"
#2910000
b10100111010101111000000001101101 !
b10100111010101111000000001101101 )
1"
#2920000
0"
#2930000
b11010011100010111100000000110101 !
b11010011100010111100000000110101 )
1"
#2940000
0"
#2950000
b11101001111001011110000000011001 !
b11101001111001011110000000011001 )
1"
#2960000
0"
#2970000
b11110100110100101111000000001111 !
b11110100110100101111000000001111 )
1"
#2980000
0"
#2990000
b11111010010010010111100000000100 !
b11111010010010010111100000000100 )
1"
#3000000
0"
#3010000
b1111101001001001011110000000010 !
b1111101001001001011110000000010 )
1"
#3020000
0"
#3030000
b111110100100100101111000000001 !
b111110100100100101111000000001 )
1"
#3040000
0"
#3050000
b10011111011010010010111100000011 !
b10011111011010010010111100000011 )
1"
#3060000
0"
#3070000
b11001111100101001001011110000010 !
b11001111100101001001011110000010 )
1"
#3080000
0"
#3090000
b1100111110010100100101111000001 !
b1100111110010100100101111000001 )
1"
#3100000
0"
#3110000
b10110011110001010010010111100011 !
b10110011110001010010010111100011 )
1"
#3120000
0"
#3130000
b11011001110000101001001011110010 !
b11011001110000101001001011110010 )
1"
#3140000
0"
#3150000
b1101100111000010100100101111001 !
b1101100111000010100100101111001 )
1"
#3160000
0"
#3170000
b10110110010100001010010010111111 !
b10110110010100001010010010111111 )
1"
#3180000
0"
#3190000
b11011011000010000101001001011100 !
b11011011000010000101001001011100 )
1"
#3200000
0"
#3210000
b1101101100001000010100100101110 !
b1101101100001000010100100101110 )
1"
#3220000
0"
#3230000
b110110110000100001010010010111 !
b110110110000100001010010010111 )
1"
#3240000
0"
#3250000
b10011011010000010000101001001000 !
b10011011010000010000101001001000 )
1"
#3260000
0"
#3270000
b1001101101000001000010100100100 !
b1001101101000001000010100100100 )
1"
#3280000
0"
#3290000
b100110110100000100001010010010 !
b100110110100000100001010010010 )
1"
#3300000
0"
#3310000
b10011011010000010000101001001 !
b10011011010000010000101001001 )
1"
#3320000
0"
#3330000
b10001001100101000001000010100111 !
b10001001100101000001000010100111 )
1"
#3340000
0"
#3350000
b11000100111010100000100001010000 !
b11000100111010100000100001010000 )
1"
#3360000
0"
#3370000
b1100010011101010000010000101000 !
b1100010011101010000010000101000 )
1"
#3380000
0"
#3390000
b110001001110101000001000010100 !
b110001001110101000001000010100 )
1"
#3400000
0"
#3410000
b11000100111010100000100001010 !
b11000100111010100000100001010 )
1"
#3420000
0"
#3430000
b1100010011101010000010000101 !
b1100010011101010000010000101 )
1"
#3440000
0"
#3450000
b10000110000001110101000001000001 !
b10000110000001110101000001000001 )
1"
#3460000
0"
#3470000
b11000011001000111010100000100011 !
b11000011001000111010100000100011 )
1"
#3480000
0"
#3490000
b11100001101100011101010000010010 !
b11100001101100011101010000010010 )
1"
#3500000
0"
#3510000
b1110000110110001110101000001001 !
b1110000110110001110101000001001 )
1"
#3520000
0"
#3530000
b10111000010011000111010100000111 !
b10111000010011000111010100000111 )
1"
#3540000
0"
#3550000
b11011100000001100011101010000000 !
b11011100000001100011101010000000 )
1"
#3560000
0"
#3570000
b1101110000000110001110101000000 !
b1101110000000110001110101000000 )
1"
#3580000
0"
#3590000
b110111000000011000111010100000 !
b110111000000011000111010100000 )
1"
#3600000
0"
#3610000
b11011100000001100011101010000 !
b11011100000001100011101010000 )
1"
#3620000
0"
#3630000
b1101110000000110001110101000 !
b1101110000000110001110101000 )
1"
#3640000
0"
#3650000
b110111000000011000111010100 !
b110111000000011000111010100 )
1"
#3660000
0"
#3670000
b11011100000001100011101010 !
b11011100000001100011101010 )
1"
#3680000
0"
#3690000
b1101110000000110001110101 !
b1101110000000110001110101 )
1"
#3700000
0"
#3710000
b10000000111111000000011000111001 !
b10000000111111000000011000111001 )
1"
#3720000
0"
#3730000
b11000000010111100000001100011111 !
b11000000010111100000001100011111 )
1"
#3740000
0"
#3750000
b11100000000011110000000110001100 !
b11100000000011110000000110001100 )
1"
#3760000
0"
#3770000
b1110000000001111000000011000110 !
b1110000000001111000000011000110 )
1"
#3780000
0"
#3790000
b111000000000111100000001100011 !
b111000000000111100000001100011 )
1"
#3800000
0"
#3810000
b10011100001000011110000000110010 !
b10011100001000011110000000110010 )
1"
#3820000
0"
#3830000
b1001110000100001111000000011001 !
b1001110000100001111000000011001 )
1"
#3840000
0"
#3850000
b10100111001010000111100000001111 !
b10100111001010000111100000001111 )
1"
#3860000
0"
#3870000
b11010011101101000011110000000100 !
b11010011101101000011110000000100 )
1"
#3880000
0"
#3890000
b1101001110110100001111000000010 !
b1101001110110100001111000000010 )
1"
#3900000
0"
#3910000
b110100111011010000111100000001 !
b110100111011010000111100000001 )
1"
#3920000
0"
#3930000
b10011010010101101000011110000011 !
b10011010010101101000011110000011 )
1"
#3940000
0"
#3950000
b11001101000010110100001111000010 !
b11001101000010110100001111000010 )
1"
#3960000
0"
#3970000
b1100110100001011010000111100001 !
b1100110100001011010000111100001 )
1"
#3980000
0"
#3990000
b10110011011000101101000011110011 !
b10110011011000101101000011110011 )
1"
#4000000
0"
#4010000
b11011001100100010110100001111010 !
b11011001100100010110100001111010 )
1"
#4020000
0"
#4030000
b1101100110010001011010000111101 !
b1101100110010001011010000111101 )
1"
#4040000
0"
#4050000
b10110110010001000101101000011101 !
b10110110010001000101101000011101 )
1"
#4060000
0"
#4070000
b11011011000000100010110100001101 !
b11011011000000100010110100001101 )
1"
#4080000
0"
#4090000
b11101101101000010001011010000101 !
b11101101101000010001011010000101 )
1"
#4100000
0"
#4110000
1"
0#
